spead2/__init__.py
spead2/__init__.pyi
spead2/_spead2.cpython-310-x86_64-linux-gnu.so
spead2/_version.py
spead2/numba.py
spead2/numba.pyi
spead2/py.typed
spead2/recv/__init__.py
spead2/recv/__init__.pyi
spead2/recv/asyncio.py
spead2/recv/asyncio.pyi
spead2/recv/numba.py
spead2/recv/numba.pyi
spead2/recv/stream_stat_indices.py
spead2/recv/stream_stat_indices.pyi
spead2/send/__init__.py
spead2/send/__init__.pyi
spead2/send/asyncio.py
spead2/send/asyncio.pyi
spead2/tools/__init__.py
spead2/tools/bench_asyncio.py
spead2/tools/cmdline.py
spead2/tools/recv_asyncio.py
spead2/tools/send_asyncio.py
spead2.libs/libpcap-2fe6be78.so.1.10.6
spead2-4.4.1.dist-info/METADATA
spead2-4.4.1.dist-info/WHEEL
spead2-4.4.1.dist-info/entry_points.txt
spead2-4.4.1.dist-info/RECORD
spead2-4.4.1.dist-info/licenses/COPYING
spead2-4.4.1.dist-info/licenses/COPYING.LESSER
