Metadata-Version: 2.4
Name: spead2
Version: 4.4.1
Summary: High-performance SPEAD implementation
Author-Email: Bruce Merry <bmerry@sarao.ac.za>
License-Expression: LGPL-3.0-or-later
License-File: COPYING
License-File: COPYING.LESSER
Classifier: Development Status :: 5 - Production/Stable
Classifier: Framework :: AsyncIO
Classifier: Intended Audience :: Developers
Classifier: Operating System :: POSIX
Classifier: Programming Language :: Python :: 3
Classifier: Topic :: Software Development :: Libraries
Classifier: Topic :: System :: Networking
Project-URL: Homepage, https://github.com/ska-sa/spead2
Project-URL: Repository, https://github.com/ska-sa/spead2
Project-URL: Documentation, https://spead2.readthedocs.io/
Project-URL: Changelog, https://spead2.readthedocs.io/en/latest/changelog.html
Requires-Python: >=3.9
Requires-Dist: numpy>=1.9.2
Provides-Extra: test
Requires-Dist: netifaces2; extra == "test"
Requires-Dist: pytest; extra == "test"
Requires-Dist: pytest-asyncio; extra == "test"
Requires-Dist: pytest-timeout; extra == "test"
Provides-Extra: test-numba
Requires-Dist: numba; extra == "test-numba"
Requires-Dist: scipy; extra == "test-numba"
